hmanim/__init__.py
hmanim/native/__init__.py
hmanim/native/annular_sector.py
hmanim/native/arc.py
hmanim/native/background.py
hmanim/native/circle.py
hmanim/native/closed_arc.py
hmanim/native/dot.py
hmanim/native/graph.py
hmanim/native/line.py
hmanim/native/point.py
hmanim/native/polygon.py
hmanim/native/polygonal_chain.py
hmanim/native/rotate.py
hmanim/native/rotated_translate.py
hmanim/native/scale.py
hmanim/native/set_curvature.py
hmanim/native/translate.py
hmanim/native/translate_and_rotate.py
hmanim/native/vmobject.py
hmanim/poincare/__init__.py
hmanim/poincare/disk.py
hmanim/poincare/dot.py
hmanim/poincare/ideal_point.py
hmanim/poincare/ideal_polygon.py
hmanim/poincare/line.py
hmanim/poincare/point.py
hmanim/poincare/polygon.py
hmanim-0.1.0.dist-info/LICENSE
hmanim-0.1.0.dist-info/METADATA
hmanim-0.1.0.dist-info/WHEEL
hmanim-0.1.0.dist-info/top_level.txt
hmanim-0.1.0.dist-info/RECORD
