Metadata-Version: 2.1
Name: hmanim
Version: 0.1.0
Summary: The hyperbolic extension of manim!
Author-email: Maximilian Katzmann <max.katzmann@gmail.com>
License: MIT License
Project-URL: Homepage, https://github.com/maxkatzmann/hmanim
Keywords: animation,visualization,hyperbolic,geometry,math
Classifier: Programming Language :: Python
Classifier: Programming Language :: Python :: 3
Requires-Python: >=3.12
License-File: LICENSE
Requires-Dist: colour
Requires-Dist: manim
Requires-Dist: networkx
Requires-Dist: numpy
Provides-Extra: dev
